py_tree_sitter_spthy/__init__.py
py_tree_sitter_spthy/__init__.pyi
py_tree_sitter_spthy-1.2.1.dist-info/licenses/LICENSE
tree_sitter_spthy/__init__.py
tree_sitter_spthy/__init__.pyi
tree_sitter_spthy/_binding.cp313-win_arm64.pyd
tree_sitter_spthy/py.typed
py_tree_sitter_spthy-1.2.1.dist-info/METADATA
py_tree_sitter_spthy-1.2.1.dist-info/WHEEL
py_tree_sitter_spthy-1.2.1.dist-info/top_level.txt
py_tree_sitter_spthy-1.2.1.dist-info/RECORD
