Metadata-Version: 2.4
Name: py-tree-sitter-spthy
Version: 1.2.1
Summary: Tree-sitter parser for Spthy language (Tamarin Prover)
Author-email: Luca Mandrelli <luca.mandrelli@icloud.com>
License-Expression: GPL-3.0-or-later
Project-URL: Homepage, https://github.com/lmandrelli/py-tree-sitter-spthy
Project-URL: Repository, https://github.com/lmandrelli/py-tree-sitter-spthy
Project-URL: Issues, https://github.com/lmandrelli/py-tree-sitter-spthy/issues
Project-URL: Bug Tracker, https://github.com/lmandrelli/py-tree-sitter-spthy/issues
Project-URL: Documentation, https://github.com/lmandrelli/py-tree-sitter-spthy/blob/main/README.md
Project-URL: Source Code, https://github.com/lmandrelli/py-tree-sitter-spthy
Keywords: tree-sitter,parser,spthy,tamarin,protocol,verification,security,formal-methods,syntax-tree,parsing
Classifier: Development Status :: 5 - Production/Stable
Classifier: Intended Audience :: Developers
Classifier: Operating System :: MacOS
Classifier: Operating System :: Microsoft :: Windows
Classifier: Operating System :: POSIX :: Linux
Classifier: Programming Language :: Python :: 3
Classifier: Programming Language :: Python :: 3.9
Classifier: Programming Language :: Python :: 3.10
Classifier: Programming Language :: Python :: 3.11
Classifier: Programming Language :: Python :: 3.12
Classifier: Programming Language :: Python :: 3.13
Classifier: Programming Language :: Python :: Implementation :: CPython
Classifier: Topic :: Software Development :: Libraries :: Python Modules
Classifier: Topic :: Text Processing :: Linguistic
Classifier: Topic :: Security :: Cryptography
Classifier: Topic :: Scientific/Engineering
Requires-Python: >=3.9
License-File: LICENSE
Requires-Dist: tree-sitter>=0.20.0
Provides-Extra: dev
Requires-Dist: pytest>=6.0; extra == "dev"
Requires-Dist: black>=22.0; extra == "dev"
Requires-Dist: flake8>=4.0; extra == "dev"
Dynamic: license-file
